[{
      "id":"1722057683",
      "type":"Будинок",
      "page":"",
      "rent":"",
      "rooms":"4",
      "surface":"210",
      "surface_land":"600",
      "price":"$140000",
      "price_sqmt":"",
      "floor":"",
      "floors":"2",
      "parking":"Прибудинкова приватна огороджена територія, гараж",
      "region":"",
      "location":"м. Харків",
      "address":"в'їзд 1-й Тираспільський, 5 (станція метро Холодна гора), Новобаварський район",
      "object":"",
      "coordinates":"49.929926,36.192916",
      "date":"2024-07-27",
      "seller":"Костянтин Пересічанський",
      "phone":"380970424650","description":"Вторинна житлова нерухомість, житло відремонтоване з меблями і технікою, придатне і готове для проживання",
      "link":"/region/city/kharkiv/house/selling-1722057683.html","images":""},{
      "id":"1708346290",
      "type":"Будинок",
      "page":"",
      "rent":"",
      "rooms":"3",
      "surface":"55",
      "surface_land":"500",
      "price":"$35000",
      "price_sqmt":"",
      "floor":"",
      "floors":"1",
      "parking":"Прибудинкова територія",
      "region":"",
      "location":"м. Харків",
      "address":"вул. Шолохова, 63, Немишлянський район",
      "object":"",
      "coordinates":"49.938829,36.334307",
      "date":"2024-02-19",
      "seller":"Вєроніка Зубарєва",
      "phone":"380965692307","description":"Вторинне житло, придатне для проживання",
      "link":"/region/city/kharkiv/house/selling-1708346290.html","images":""},{
      "id":"1720000294",
      "type":"Будинок",
      "page":"",
      "rent":"",
      "rooms":"5",
      "surface":"315.8",
      "surface_land":"1000",
      "price":"$120000",
      "price_sqmt":"",
      "floor":"",
      "floors":"2",
      "parking":"Прибудинкова огороджена територія, гараж",
      "region":"",
      "location":"м. Харків",
      "address":"провулок Канівський, 5, Основ’янський район",
      "object":"",
      "coordinates":"49.904992,36.225131",
      "date":"2024-02-19",
      "seller":"Олександр Щегольський",
      "phone":"380503640595","description":"Вторинне житло, придатне для проживання",
      "link":"/region/city/kharkiv/house/selling-1720000294.html","images":""},{
      "id":"1708346797",
      "type":"Будинок",
      "page":"",
      "rent":"",
      "rooms":"1",
      "surface":"35.2",
      "surface_land":"300",
      "price":"$17000",
      "price_sqmt":"",
      "floor":"",
      "floors":"1",
      "parking":"Прибудинкова територія",
      "region":"",
      "location":"м. Харків",
      "address":"провулок Цигарівський, 41, Основ’янський район",
      "object":"",
      "coordinates":"49.970554,36.232007",
      "date":"2024-02-19",
      "seller":"Каріна Рєчкіна",
      "phone":"380667154827","description":"Вторинне житло, придатне для проживання",
      "link":"/region/city/kharkiv/house/selling-1708346797.html","images":""},{
      "id":"1708344968",
      "type":"Будинок",
      "page":"",
      "rent":"",
      "rooms":"4",
      "surface":"168",
      "surface_land":"1650",
      "price":"$95000",
      "price_sqmt":"",
      "floor":"",
      "floors":"1Г",
      "parking":"Прибудинкова територія",
      "region":"",
      "location":"м. Харків",
      "address":"вул. Крамаренківська, 120, Немишлянський район",
      "object":"",
      "coordinates":"49.999226,36.386522",
      "date":"2024-02-19",
      "seller":"Катерина Рибалка",
      "phone":"380669085745","description":"Новозведене житло, потребує будівельних і ремонтно-оздоблювальних робіт",
      "link":"/region/city/kharkiv/house/selling-1708344968.html","images":""},{
      "id":"1708343961",
      "type":"Будинок",
      "page":"",
      "rent":"",
      "rooms":"3",
      "surface":"102",
      "surface_land":"600",
      "price":"$108000",
      "price_sqmt":"",
      "floor":"",
      "floors":"1Г",
      "parking":"Прибудинкова територія",
      "region":"",
      "location":"м. Харків",
      "address":"вул. Петропавлівська, 62Б, Київський район",
      "object":"",
      "coordinates":"50.009056,36.264171",
      "date":"2024-02-19",
      "seller":"Юлія Ніненко",
      "phone":"380507009826","description":"Вторинне відремонтоване житло з меблями і технікою, придатне і готове для проживання",
      "link":"/region/city/kharkiv/house/selling-1708343961.html","images":[{"src":"1_house.jpg","alt":"Будинок в м. Харків","title":"Будинок по вул. Петропавлівська, 62Б, Київський район в м. Харків"},{"src":"2_livingroom.jpg","alt":"Будинок в м. Харків","title":"Будинок по вул. Петропавлівська, 62Б, Київський район в м. Харків"},{"src":"3_bedroom.jpg","alt":"Будинок в м. Харків","title":"Будинок по вул. Петропавлівська, 62Б, Київський район в м. Харків"},{"src":"4_restroom.jpg","alt":"Будинок в м. Харків","title":"Будинок по вул. Петропавлівська, 62Б, Київський район в м. Харків"}]}]
